{
    "adult": false,
    "backdrop_path": "/1OGpHtpa58vmIOUyHVQJOSKjkJQ.jpg",
    "genre_ids": [
        37
    ],
    "id": 4934,
    "original_language": "en",
    "original_title": "Firecreek",
    "overview": "A peace-loving, part-time sheriff in the small town of Firecreek must take a stand when a gang of vicious outlaws takes over his town.",
    "popularity": 49.7361,
    "poster_path": "/zypuu5aEoyM5tadMAkbNm3Kccq9.jpg",
    "release_date": "1968-01-24",
    "title": "Firecreek",
    "video": false,
    "vote_average": 6.322,
    "vote_count": 73
}