{
    "adult": false,
    "backdrop_path": "/hYgUkH7TusddHRtelj53I6gFOWR.jpg",
    "genre_ids": [
        28,
        53
    ],
    "id": 799882,
    "original_language": "en",
    "original_title": "The Bluff",
    "overview": "When her tranquil life on a remote island is shattered by the return of her vengeful former captain, a skilled ex-pirate must confront her bloody past and unleash her deadly talents to save her family from a ruthless siege.",
    "popularity": 193.2064,
    "poster_path": "/w0jwjFmRu2or7LQqh1tSMFjq0At.jpg",
    "release_date": "2026-02-17",
    "title": "The Bluff",
    "video": false,
    "vote_average": 6.333,
    "vote_count": 273
}